cognitivefactory/interactive_clustering_gui/__init__.py
cognitivefactory/interactive_clustering_gui/__main__.py
cognitivefactory/interactive_clustering_gui/app.py
cognitivefactory/interactive_clustering_gui/backgroundtasks.py
cognitivefactory/interactive_clustering_gui/cli.py
cognitivefactory/interactive_clustering_gui/css/new_styles.css
cognitivefactory/interactive_clustering_gui/css/styles.css
cognitivefactory/interactive_clustering_gui/html/_base.html
cognitivefactory/interactive_clustering_gui/html/analytics.html
cognitivefactory/interactive_clustering_gui/html/constraint_annotation.html
cognitivefactory/interactive_clustering_gui/html/constraints.html
cognitivefactory/interactive_clustering_gui/html/error.html
cognitivefactory/interactive_clustering_gui/html/help.html
cognitivefactory/interactive_clustering_gui/html/project_home.html
cognitivefactory/interactive_clustering_gui/html/projects_listing.html
cognitivefactory/interactive_clustering_gui/html/settings.html
cognitivefactory/interactive_clustering_gui/html/texts.html
cognitivefactory/interactive_clustering_gui/html/welcome.html
cognitivefactory/interactive_clustering_gui/js/analytics.js
cognitivefactory/interactive_clustering_gui/js/annotation.js
cognitivefactory/interactive_clustering_gui/js/collapsing.js
cognitivefactory/interactive_clustering_gui/js/constraints.js
cognitivefactory/interactive_clustering_gui/js/goto.js
cognitivefactory/interactive_clustering_gui/js/projects.js
cognitivefactory/interactive_clustering_gui/js/projects_listing.js
cognitivefactory/interactive_clustering_gui/js/settings.js
cognitivefactory/interactive_clustering_gui/js/status.js
cognitivefactory/interactive_clustering_gui/js/tasks.js
cognitivefactory/interactive_clustering_gui/models/__init__.py
cognitivefactory/interactive_clustering_gui/models/queries.py
cognitivefactory/interactive_clustering_gui/models/settings.py
cognitivefactory/interactive_clustering_gui/models/states.py
cognitivefactory_interactive_clustering_gui-0.4.1.dist-info/entry_points.txt
cognitivefactory_interactive_clustering_gui-0.4.1.dist-info/WHEEL
cognitivefactory_interactive_clustering_gui-0.4.1.dist-info/METADATA
cognitivefactory_interactive_clustering_gui-0.4.1.dist-info/licenses/LICENSE.md
cognitivefactory_interactive_clustering_gui-0.4.1.dist-info/RECORD
