Metadata-Version: 2.1
Name: cognitivefactory-interactive-clustering-gui
Version: 0.4.1
Summary: A web application designed for NLP data annotation using Interactive Clustering methodology.
License: CECILL-C
Keywords: natural-language-processing,constraints,annotation-tool,interactive-clustering,constraints-annotation
Author-email: Erwan Schild <erwan.schild@e-i.com>
Requires-Python: >=3.8
Classifier: Development Status :: 4 - Beta
Classifier: Intended Audience :: Developers
Classifier: Programming Language :: Python
Classifier: Programming Language :: Python :: 3
Classifier: Programming Language :: Python :: 3 :: Only
Classifier: Programming Language :: Python :: 3.8
Classifier: Programming Language :: Python :: 3.9
Classifier: Topic :: Documentation
Classifier: Topic :: Software Development
Classifier: Topic :: Software Development :: Documentation
Classifier: Topic :: Utilities
Classifier: Typing :: Typed
Requires-Dist: cognitivefactory-interactive-clustering>=0.5.2
Requires-Dist: fastapi>=0.65.2
Requires-Dist: filelock>=3.0.12
Requires-Dist: jinja2>=3.0.1
Requires-Dist: loguru>=0.5.3
Requires-Dist: openpyxl>=3.0.7
Requires-Dist: pandas>=1.1.4
Requires-Dist: prometheus-fastapi-instrumentator>=5.5.1
Requires-Dist: python-multipart>=0.0.5
Requires-Dist: scikit-learn>=0.24.1
Requires-Dist: setuptools>=65.5.1
Requires-Dist: uvicorn>=0.12.2
Requires-Dist: zipp>=3.5.0
Project-URL: Changelog, https://cognitivefactory.github.io/interactive-clustering-gui/changelog
Project-URL: Discussions, https://github.com/cognitivefactory/interactive-clustering-gui/discussions
Project-URL: Documentation, https://cognitivefactory.github.io/interactive-clustering-gui
Project-URL: Homepage, https://cognitivefactory.github.io/interactive-clustering-gui
Project-URL: Issues, https://github.com/cognitivefactory/interactive-clustering-gui/issues
Project-URL: Repository, https://github.com/cognitivefactory/interactive-clustering-gui
